s6r_hubspot/__init__.py
s6r_hubspot/custom_object.py
s6r_hubspot/hub_db.py
s6r_hubspot/hubspot.py
tests/unit_test.py
s6r_hubspot-1.0.14.dist-info/LICENSE
s6r_hubspot-1.0.14.dist-info/METADATA
s6r_hubspot-1.0.14.dist-info/WHEEL
s6r_hubspot-1.0.14.dist-info/top_level.txt
s6r_hubspot-1.0.14.dist-info/RECORD
