Metadata-Version: 2.2
Name: s6r-hubspot
Version: 1.0.14
Summary: Hubspot API client
Author-email: Michel Perrocheau <michel@scalizer.fr>
License:                    GNU LESSER GENERAL PUBLIC LICENSE
Project-URL: Homepage, https://github.com/ScalizerOrg/s6r-hubspot
Keywords: hubspot
Classifier: License :: OSI Approved :: GNU Lesser General Public License v3 (LGPLv3)
Classifier: Programming Language :: Python
Classifier: Programming Language :: Python :: 3
Requires-Python: >=3.9
License-File: LICENSE
Provides-Extra: dev
Requires-Dist: twine; extra == "dev"
Requires-Dist: bumpver; extra == "dev"
Requires-Dist: pip-tools; extra == "dev"
Requires-Dist: pytest; extra == "dev"
Requires-Dist: check-manifest; extra == "dev"
